slitflow/__init__.py
slitflow/data.py
slitflow/info.py
slitflow/manager.py
slitflow/name.py
slitflow/setindex.py
slitflow/setreqs.py
slitflow/fig/__init__.py
slitflow/fig/bar.py
slitflow/fig/figure.py
slitflow/fig/image.py
slitflow/fig/line.py
slitflow/fig/scatter.py
slitflow/fig/style.py
slitflow/fig/trajectory.py
slitflow/fun/__init__.py
slitflow/fun/img.py
slitflow/fun/misc.py
slitflow/fun/palette.py
slitflow/fun/sort.py
slitflow/img/__init__.py
slitflow/img/calc.py
slitflow/img/convert.py
slitflow/img/create.py
slitflow/img/filter.py
slitflow/img/image.py
slitflow/img/montage.py
slitflow/img/noise.py
slitflow/img/plot.py
slitflow/img/proc.py
slitflow/load/__init__.py
slitflow/load/table.py
slitflow/load/tif.py
slitflow/loc/__init__.py
slitflow/loc/convert.py
slitflow/loc/fit.py
slitflow/loc/mask.py
slitflow/loc/random.py
slitflow/tbl/__init__.py
slitflow/tbl/convert.py
slitflow/tbl/create.py
slitflow/tbl/filter.py
slitflow/tbl/math.py
slitflow/tbl/proc.py
slitflow/tbl/stat.py
slitflow/tbl/table.py
slitflow/trj/__init__.py
slitflow/trj/filter.py
slitflow/trj/msd.py
slitflow/trj/random.py
slitflow/trj/subtrj.py
slitflow/trj/wfastspt.py
slitflow/trj/wtrackpy.py
slitflow/trj/wtramway.py
slitflow/user/__init__.py
slitflow/user/template.py
tests/__init__.py
tests/test_data.py
tests/test_fig_bar.py
tests/test_fig_figure.py
tests/test_fig_image.py
tests/test_fig_line.py
tests/test_fig_scatter.py
tests/test_fig_style.py
tests/test_fig_trajectory.py
tests/test_fun.py
tests/test_getting_started.py
tests/test_img_calc.py
tests/test_img_create.py
tests/test_img_filter.py
tests/test_img_image.py
tests/test_img_montage.py
tests/test_img_noise.py
tests/test_img_plot.py
tests/test_img_proc.py
tests/test_info.py
tests/test_load_table.py
tests/test_load_tif.py
tests/test_loc_convert.py
tests/test_loc_fit.py
tests/test_loc_mask.py
tests/test_loc_random.py
tests/test_manager.py
tests/test_name.py
tests/test_setindex.py
tests/test_setreqs.py
tests/test_tbl_convert.py
slitflow-0.1.5.dist-info/LICENCE
slitflow-0.1.5.dist-info/METADATA
slitflow-0.1.5.dist-info/WHEEL
slitflow-0.1.5.dist-info/top_level.txt
slitflow-0.1.5.dist-info/RECORD
