Metadata-Version: 2.1
Name: slitflow
Version: 0.1.5
Summary: A Python framework for single-molecule dynamics and localization analysis
Author: Yuma Ito
Author-email: yitou@bio.titech.ac.jp
Classifier: Programming Language :: Python :: 3
Classifier: License :: OSI Approved :: BSD License
Classifier: Intended Audience :: Science/Research
Classifier: Intended Audience :: Developers
Requires-Python: <3.11,>=3.8
License-File: LICENCE
Requires-Dist: numpy
Requires-Dist: pandas <2.0.0
Requires-Dist: matplotlib
Requires-Dist: tifffile
Requires-Dist: tqdm
Requires-Dist: psutil
Requires-Dist: opencv-python
Requires-Dist: scipy
Requires-Dist: scikit-learn
Requires-Dist: scikit-image
Requires-Dist: netgraph
Provides-Extra: dev
Requires-Dist: flake8 ; extra == 'dev'
Requires-Dist: autopep8 ; extra == 'dev'
Requires-Dist: pytest ; extra == 'dev'
Requires-Dist: pytest-cov ; extra == 'dev'
Requires-Dist: sphinx ; extra == 'dev'
Requires-Dist: sphinx-rtd-theme ; extra == 'dev'
Requires-Dist: docutils ==0.16 ; extra == 'dev'
Requires-Dist: doc8 ; extra == 'dev'
Requires-Dist: notebook ; extra == 'dev'
Requires-Dist: ipywidgets ; extra == 'dev'
Provides-Extra: full
Requires-Dist: scikit-posthocs ; extra == 'full'
Requires-Dist: trackpy ; extra == 'full'
Requires-Dist: tramway ; extra == 'full'
